{
  "filter_paths": "node_modules,lib/forge-std,@openzeppelin/contracts,test,TestRaffleSystem.sol,SimpleMonolithicFactory.sol,BaseRaffleSystem.sol,MonolithicBaseFactory.sol,RaffleContractSecure.sol,RaffleContractSecureV2.sol,RaffleFactorySecure.sol,RaffleFactorySecureV2.sol,RaffleFactorySecureV3.sol,RaffleFactoryBaseFinal.sol,RaffleFactoryBaseV3.sol,SimpleBaseFactory.sol,MinimalTestFactory.sol,MockERC721.sol",
  "exclude_dependencies": true,
  "exclude_informational": false,
  "exclude_low": false,
  "exclude_medium": false,
  "exclude_high": false,
  "solc_remaps": [
    "@openzeppelin/contracts=node_modules/@openzeppelin/contracts"
  ],
  "detectors_to_exclude": [
    "pragma",
    "solc-version",
    "low-level-calls",
    "weak-prng",
    "timestamp",
    "naming-convention",
    "constable-states"
  ]
}